LICENSE.rst
MANIFEST.in
README.rst
main.py
setup.py
intelligent_tracker/__init__.py
intelligent_tracker/array_utils.py
intelligent_tracker/core.py
intelligent_tracker/detectors.py
intelligent_tracker/figures.py
intelligent_tracker/forms.py
intelligent_tracker/geometry.py
intelligent_tracker/high_objects.py
intelligent_tracker/periferials.py
intelligent_tracker/persistence.py
intelligent_tracker.egg-info/PKG-INFO
intelligent_tracker.egg-info/SOURCES.txt
intelligent_tracker.egg-info/dependency_links.txt
intelligent_tracker.egg-info/requires.txt
intelligent_tracker.egg-info/top_level.txt